{
  "data": {
    "312410196": {
      "phone": "+7 (812) 218-96-38",
      "notFormattedPhone": "78122189638"
    },
    "307204156": {
      "phone": "+7 (812) 218-96-38",
      "notFormattedPhone": "78122189638"
    },
    "298782225": {
      "phone": "+7 (812) 218-96-38",
      "notFormattedPhone": "78122189638"
    },
    "318130018": {
      "phone": "+7 (812) 218-96-38",
      "notFormattedPhone": "78122189638"
    },
    "317005959": {
      "phone": "+7 (812) 218-96-38",
      "notFormattedPhone": "78122189638"
    },
    "285185522": {
      "phone": "+7 (812) 218-96-38",
      "notFormattedPhone": "78122189638"
    },
    "310858036": {
      "phone": "+7 (812) 218-96-38",
      "notFormattedPhone": "78122189638"
    },
    "312466139": {
      "phone": "+7 (812) 218-96-38",
      "notFormattedPhone": "78122189638"
    },
    "317665228": {
      "phone": "+7 (812) 218-96-38",
      "notFormattedPhone": "78122189638"
    },
    "302097355": {
      "phone": "+7 (812) 218-96-38",
      "notFormattedPhone": "78122189638"
    },
    "316509086": {
      "phone": "+7 (812) 218-96-38",
      "notFormattedPhone": "78122189638"
    },
    "314496877": {
      "phone": "+7 (812) 218-96-38",
      "notFormattedPhone": "78122189638"
    },
    "318582820": {
      "phone": "+7 (812) 218-96-38",
      "notFormattedPhone": "78122189638"
    },
    "309536248": {
      "phone": "+7 (812) 218-96-38",
      "notFormattedPhone": "78122189638"
    },
    "295387701": {
      "phone": "+7 (812) 218-96-38",
      "notFormattedPhone": "78122189638"
    },
    "318583533": {
      "phone": "+7 (812) 218-96-38",
      "notFormattedPhone": "78122189638"
    },
    "308898203": {
      "phone": "+7 (812) 218-96-38",
      "notFormattedPhone": "78122189638"
    },
    "316879043": {
      "phone": "+7 (812) 218-96-38",
      "notFormattedPhone": "78122189638"
    },
    "302097103": {
      "phone": "+7 (812) 218-96-38",
      "notFormattedPhone": "78122189638"
    },
    "314832113": {
      "phone": "+7 (812) 218-96-38",
      "notFormattedPhone": "78122189638"
    },
    "300193984": {
      "phone": "+7 (812) 218-96-38",
      "notFormattedPhone": "78122189638"
    },
    "314600602": {
      "phone": "+7 (812) 218-96-38",
      "notFormattedPhone": "78122189638"
    },
    "317005034": {
      "phone": "+7 (812) 218-96-38",
      "notFormattedPhone": "78122189638"
    },
    "318496324": {
      "phone": "+7 (812) 218-96-38",
      "notFormattedPhone": "78122189638"
    },
    "300091203": {
      "phone": "+7 (812) 218-96-38",
      "notFormattedPhone": "78122189638"
    },
    "314600604": {
      "phone": "+7 (812) 218-96-38",
      "notFormattedPhone": "78122189638"
    },
    "317135419": {
      "phone": "+7 (812) 218-96-38",
      "notFormattedPhone": "78122189638"
    },
    "300856267": {
      "phone": "+7 (812) 218-96-38",
      "notFormattedPhone": "78122189638"
    },
    "318130176": {
      "phone": "+7 (812) 218-96-38",
      "notFormattedPhone": "78122189638"
    },
    "318375368": {
      "phone": "+7 (812) 218-96-38",
      "notFormattedPhone": "78122189638"
    },
    "318375964": {
      "phone": "+7 (812) 218-96-38",
      "notFormattedPhone": "78122189638"
    },
    "317381619": {
      "phone": "+7 (812) 218-96-38",
      "notFormattedPhone": "78122189638"
    },
    "314496254": {
      "phone": "+7 (812) 218-96-38",
      "notFormattedPhone": "78122189638"
    },
    "308033998": {
      "phone": "+7 (812) 218-96-38",
      "notFormattedPhone": "78122189638"
    },
    "295663107": {
      "phone": "+7 (812) 218-96-38",
      "notFormattedPhone": "78122189638"
    },
    "307839522": {
      "phone": "+7 (812) 218-96-38",
      "notFormattedPhone": "78122189638"
    },
    "309863832": {
      "phone": "+7 (812) 218-96-38",
      "notFormattedPhone": "78122189638"
    },
    "318582732": {
      "phone": "+7 (812) 218-96-38",
      "notFormattedPhone": "78122189638"
    },
    "317569220": {
      "phone": "+7 (812) 218-96-38",
      "notFormattedPhone": "78122189638"
    },
    "309862890": {
      "phone": "+7 (812) 218-96-38",
      "notFormattedPhone": "78122189638"
    },
    "312921890": {
      "phone": "+7 (812) 218-96-38",
      "notFormattedPhone": "78122189638"
    },
    "289027248": {
      "phone": "+7 (812) 218-96-38",
      "notFormattedPhone": "78122189638"
    },
    "316635131": {
      "phone": "+7 (812) 218-96-38",
      "notFormattedPhone": "78122189638"
    },
    "307592838": {
      "phone": "+7 (812) 218-96-38",
      "notFormattedPhone": "78122189638"
    },
    "318600080": {
      "phone": "+7 (812) 218-96-38",
      "notFormattedPhone": "78122189638"
    },
    "318181509": {
      "phone": "+7 (812) 218-96-38",
      "notFormattedPhone": "78122189638"
    },
    "308898306": {
      "phone": "+7 (812) 218-96-38",
      "notFormattedPhone": "78122189638"
    },
    "318011295": {
      "phone": "+7 (812) 218-96-38",
      "notFormattedPhone": "78122189638"
    },
    "312897889": {
      "phone": "+7 (812) 218-96-38",
      "notFormattedPhone": "78122189638"
    },
    "316477385": {
      "phone": "+7 (812) 218-96-38",
      "notFormattedPhone": "78122189638"
    },
    "311789284": {
      "phone": "+7 (812) 218-96-38",
      "notFormattedPhone": "78122189638"
    },
    "309863728": {
      "phone": "+7 (812) 218-96-38",
      "notFormattedPhone": "78122189638"
    },
    "311196396": {
      "phone": "+7 (812) 218-96-38",
      "notFormattedPhone": "78122189638"
    },
    "317134181": {
      "phone": "+7 (812) 218-96-38",
      "notFormattedPhone": "78122189638"
    },
    "295663246": {
      "phone": "+7 (812) 218-96-38",
      "notFormattedPhone": "78122189638"
    },
    "317807409": {
      "phone": "+7 (812) 218-96-38",
      "notFormattedPhone": "78122189638"
    },
    "306358698": {
      "phone": "+7 (812) 218-96-38",
      "notFormattedPhone": "78122189638"
    },
    "307321575": {
      "phone": "+7 (812) 218-96-38",
      "notFormattedPhone": "78122189638"
    },
    "317132904": {
      "phone": "+7 (812) 218-96-38",
      "notFormattedPhone": "78122189638"
    },
    "289027009": {
      "phone": "+7 (812) 218-96-38",
      "notFormattedPhone": "78122189638"
    },
    "307314376": {
      "phone": "+7 (812) 218-96-38",
      "notFormattedPhone": "78122189638"
    },
    "317134981": {
      "phone": "+7 (812) 218-96-38",
      "notFormattedPhone": "78122189638"
    },
    "318375726": {
      "phone": "+7 (812) 218-96-38",
      "notFormattedPhone": "78122189638"
    },
    "317796258": {
      "phone": "+7 (812) 218-96-38",
      "notFormattedPhone": "78122189638"
    },
    "314475385": {
      "phone": "+7 (812) 218-96-38",
      "notFormattedPhone": "78122189638"
    },
    "294210902": {
      "phone": "+7 (812) 218-96-38",
      "notFormattedPhone": "78122189638"
    },
    "317804264": {
      "phone": "+7 (812) 218-96-38",
      "notFormattedPhone": "78122189638"
    },
    "318375310": {
      "phone": "+7 (812) 218-96-38",
      "notFormattedPhone": "78122189638"
    },
    "295662746": {
      "phone": "+7 (812) 218-96-38",
      "notFormattedPhone": "78122189638"
    },
    "306294407": {
      "phone": "+7 (812) 218-96-38",
      "notFormattedPhone": "78122189638"
    },
    "312765675": {
      "phone": "+7 (812) 218-96-38",
      "notFormattedPhone": "78122189638"
    },
    "317134189": {
      "phone": "+7 (812) 218-96-38",
      "notFormattedPhone": "78122189638"
    },
    "309650736": {
      "phone": "+7 (812) 218-96-38",
      "notFormattedPhone": "78122189638"
    },
    "318649488": {
      "phone": "+7 (812) 218-96-38",
      "notFormattedPhone": "78122189638"
    },
    "285185598": {
      "phone": "+7 (812) 218-96-38",
      "notFormattedPhone": "78122189638"
    },
    "318062416": {
      "phone": "+7 (812) 218-96-38",
      "notFormattedPhone": "78122189638"
    },
    "318130534": {
      "phone": "+7 (812) 218-96-38",
      "notFormattedPhone": "78122189638"
    },
    "317135191": {
      "phone": "+7 (812) 218-96-38",
      "notFormattedPhone": "78122189638"
    },
    "312244029": {
      "phone": "+7 (812) 218-96-38",
      "notFormattedPhone": "78122189638"
    },
    "301696549": {
      "phone": "+7 (812) 218-96-38",
      "notFormattedPhone": "78122189638"
    },
    "309177625": {
      "phone": "+7 (812) 218-96-38",
      "notFormattedPhone": "78122189638"
    },
    "317273662": {
      "phone": "+7 (812) 218-96-38",
      "notFormattedPhone": "78122189638"
    },
    "304578930": {
      "phone": "+7 (812) 218-96-38",
      "notFormattedPhone": "78122189638"
    },
    "318634781": {
      "phone": "+7 (812) 218-96-38",
      "notFormattedPhone": "78122189638"
    },
    "314480005": {
      "phone": "+7 (812) 218-96-38",
      "notFormattedPhone": "78122189638"
    },
    "316888531": {
      "phone": "+7 (812) 218-96-38",
      "notFormattedPhone": "78122189638"
    },
    "304182632": {
      "phone": "+7 (812) 218-96-38",
      "notFormattedPhone": "78122189638"
    },
    "312003029": {
      "phone": "+7 (812) 218-96-38",
      "notFormattedPhone": "78122189638"
    },
    "300345459": {
      "phone": "+7 (812) 218-96-38",
      "notFormattedPhone": "78122189638"
    },
    "318644464": {
      "phone": "+7 (812) 218-96-38",
      "notFormattedPhone": "78122189638"
    },
    "302240510": {
      "phone": "+7 (812) 218-96-38",
      "notFormattedPhone": "78122189638"
    },
    "311802732": {
      "phone": "+7 (812) 218-96-38",
      "notFormattedPhone": "78122189638"
    },
    "318312948": {
      "phone": "+7 (812) 218-96-38",
      "notFormattedPhone": "78122189638"
    },
    "314496239": {
      "phone": "+7 (812) 218-96-38",
      "notFormattedPhone": "78122189638"
    },
    "317133836": {
      "phone": "+7 (812) 218-96-38",
      "notFormattedPhone": "78122189638"
    },
    "317133072": {
      "phone": "+7 (812) 218-96-38",
      "notFormattedPhone": "78122189638"
    },
    "316356256": {
      "phone": "+7 (812) 218-96-38",
      "notFormattedPhone": "78122189638"
    },
    "314496361": {
      "phone": "+7 (812) 218-96-38",
      "notFormattedPhone": "78122189638"
    },
    "317552724": {
      "phone": "+7 (812) 218-96-38",
      "notFormattedPhone": "78122189638"
    },
    "318600200": {
      "phone": "+7 (812) 218-96-38",
      "notFormattedPhone": "78122189638"
    },
    "314600632": {
      "phone": "+7 (812) 218-96-38",
      "notFormattedPhone": "78122189638"
    },
    "312105075": {
      "phone": "+7 (812) 218-96-38",
      "notFormattedPhone": "78122189638"
    },
    "308821832": {
      "phone": "+7 (812) 218-96-38",
      "notFormattedPhone": "78122189638"
    },
    "302340056": {
      "phone": "+7 (812) 218-96-38",
      "notFormattedPhone": "78122189638"
    },
    "317135247": {
      "phone": "+7 (812) 218-96-38",
      "notFormattedPhone": "78122189638"
    },
    "318417739": {
      "phone": "+7 (812) 218-96-38",
      "notFormattedPhone": "78122189638"
    },
    "317603949": {
      "phone": "+7 (812) 218-96-38",
      "notFormattedPhone": "78122189638"
    },
    "315627924": {
      "phone": "+7 (812) 218-96-38",
      "notFormattedPhone": "78122189638"
    },
    "306294298": {
      "phone": "+7 (812) 218-96-38",
      "notFormattedPhone": "78122189638"
    },
    "317798319": {
      "phone": "+7 (812) 218-96-38",
      "notFormattedPhone": "78122189638"
    },
    "317925142": {
      "phone": "+7 (812) 218-96-38",
      "notFormattedPhone": "78122189638"
    },
    "318647631": {
      "phone": "+7 (812) 218-96-38",
      "notFormattedPhone": "78122189638"
    },
    "314476129": {
      "phone": "+7 (812) 218-96-38",
      "notFormattedPhone": "78122189638"
    },
    "317135620": {
      "phone": "+7 (812) 218-96-38",
      "notFormattedPhone": "78122189638"
    },
    "294567605": {
      "phone": "+7 (812) 218-96-38",
      "notFormattedPhone": "78122189638"
    },
    "318375789": {
      "phone": "+7 (812) 218-96-38",
      "notFormattedPhone": "78122189638"
    },
    "305669125": {
      "phone": "+7 (812) 218-96-38",
      "notFormattedPhone": "78122189638"
    },
    "306267171": {
      "phone": "+7 (812) 218-96-38",
      "notFormattedPhone": "78122189638"
    },
    "318192635": {
      "phone": "+7 (812) 218-96-38",
      "notFormattedPhone": "78122189638"
    },
    "317134158": {
      "phone": "+7 (812) 218-96-38",
      "notFormattedPhone": "78122189638"
    },
    "315792930": {
      "phone": "+7 (812) 218-96-38",
      "notFormattedPhone": "78122189638"
    },
    "318130120": {
      "phone": "+7 (812) 218-96-38",
      "notFormattedPhone": "78122189638"
    },
    "310201995": {
      "phone": "+7 (812) 218-96-38",
      "notFormattedPhone": "78122189638"
    },
    "316796172": {
      "phone": "+7 (812) 218-96-38",
      "notFormattedPhone": "78122189638"
    },
    "303020059": {
      "phone": "+7 (812) 218-96-38",
      "notFormattedPhone": "78122189638"
    },
    "304385347": {
      "phone": "+7 (812) 218-96-38",
      "notFormattedPhone": "78122189638"
    },
    "318649257": {
      "phone": "+7 (812) 218-96-38",
      "notFormattedPhone": "78122189638"
    },
    "318582851": {
      "phone": "+7 (812) 218-96-38",
      "notFormattedPhone": "78122189638"
    },
    "260411066": {
      "phone": "+7 (812) 218-96-38",
      "notFormattedPhone": "78122189638"
    },
    "313096957": {
      "phone": "+7 (812) 218-96-38",
      "notFormattedPhone": "78122189638"
    },
    "317156334": {
      "phone": "+7 (812) 218-96-38",
      "notFormattedPhone": "78122189638"
    },
    "309177856": {
      "phone": "+7 (812) 218-96-38",
      "notFormattedPhone": "78122189638"
    },
    "308717775": {
      "phone": "+7 (812) 218-96-38",
      "notFormattedPhone": "78122189638"
    },
    "316734880": {
      "phone": "+7 (812) 218-96-38",
      "notFormattedPhone": "78122189638"
    },
    "308699719": {
      "phone": "+7 (812) 218-96-38",
      "notFormattedPhone": "78122189638"
    },
    "314497006": {
      "phone": "+7 (812) 218-96-38",
      "notFormattedPhone": "78122189638"
    },
    "317133961": {
      "phone": "+7 (812) 218-96-38",
      "notFormattedPhone": "78122189638"
    },
    "293270627": {
      "phone": "+7 (812) 218-96-38",
      "notFormattedPhone": "78122189638"
    },
    "317135321": {
      "phone": "+7 (812) 218-96-38",
      "notFormattedPhone": "78122189638"
    },
    "315622703": {
      "phone": "+7 (812) 218-96-38",
      "notFormattedPhone": "78122189638"
    },
    "313382840": {
      "phone": "+7 (812) 218-96-38",
      "notFormattedPhone": "78122189638"
    },
    "318375744": {
      "phone": "+7 (812) 218-96-38",
      "notFormattedPhone": "78122189638"
    },
    "314832110": {
      "phone": "+7 (812) 218-96-38",
      "notFormattedPhone": "78122189638"
    },
    "312774281": {
      "phone": "+7 (812) 218-96-38",
      "notFormattedPhone": "78122189638"
    },
    "293576190": {
      "phone": "+7 (812) 218-96-38",
      "notFormattedPhone": "78122189638"
    },
    "317134685": {
      "phone": "+7 (812) 218-96-38",
      "notFormattedPhone": "78122189638"
    },
    "314475997": {
      "phone": "+7 (812) 218-96-38",
      "notFormattedPhone": "78122189638"
    },
    "304776219": {
      "phone": "+7 (812) 218-96-38",
      "notFormattedPhone": "78122189638"
    },
    "307288535": {
      "phone": "+7 (812) 218-96-38",
      "notFormattedPhone": "78122189638"
    },
    "317134341": {
      "phone": "+7 (812) 218-96-38",
      "notFormattedPhone": "78122189638"
    },
    "295662691": {
      "phone": "+7 (812) 218-96-38",
      "notFormattedPhone": "78122189638"
    },
    "309294890": {
      "phone": "+7 (812) 218-96-38",
      "notFormattedPhone": "78122189638"
    },
    "314476092": {
      "phone": "+7 (812) 218-96-38",
      "notFormattedPhone": "78122189638"
    },
    "318600213": {
      "phone": "+7 (812) 218-96-38",
      "notFormattedPhone": "78122189638"
    },
    "316998688": {
      "phone": "+7 (812) 218-96-38",
      "notFormattedPhone": "78122189638"
    },
    "318130869": {
      "phone": "+7 (812) 218-96-38",
      "notFormattedPhone": "78122189638"
    },
    "318375301": {
      "phone": "+7 (812) 218-96-38",
      "notFormattedPhone": "78122189638"
    },
    "316748789": {
      "phone": "+7 (812) 218-96-38",
      "notFormattedPhone": "78122189638"
    },
    "287980980": {
      "phone": "+7 (812) 218-96-38",
      "notFormattedPhone": "78122189638"
    },
    "317926077": {
      "phone": "+7 (812) 218-96-38",
      "notFormattedPhone": "78122189638"
    },
    "317135622": {
      "phone": "+7 (812) 218-96-38",
      "notFormattedPhone": "78122189638"
    },
    "304720435": {
      "phone": "+7 (812) 218-96-38",
      "notFormattedPhone": "78122189638"
    },
    "317156312": {
      "phone": "+7 (812) 218-96-38",
      "notFormattedPhone": "78122189638"
    },
    "304272304": {
      "phone": "+7 (812) 218-96-38",
      "notFormattedPhone": "78122189638"
    },
    "299880601": {
      "phone": "+7 (812) 218-96-38",
      "notFormattedPhone": "78122189638"
    },
    "308897796": {
      "phone": "+7 (812) 218-96-38",
      "notFormattedPhone": "78122189638"
    },
    "312058201": {
      "phone": "+7 (812) 218-96-38",
      "notFormattedPhone": "78122189638"
    },
    "314496991": {
      "phone": "+7 (812) 218-96-38",
      "notFormattedPhone": "78122189638"
    },
    "316148135": {
      "phone": "+7 (812) 218-96-38",
      "notFormattedPhone": "78122189638"
    },
    "313382782": {
      "phone": "+7 (812) 218-96-38",
      "notFormattedPhone": "78122189638"
    },
    "318600266": {
      "phone": "+7 (812) 218-96-38",
      "notFormattedPhone": "78122189638"
    },
    "316509097": {
      "phone": "+7 (812) 218-96-38",
      "notFormattedPhone": "78122189638"
    },
    "309522732": {
      "phone": "+7 (812) 218-96-38",
      "notFormattedPhone": "78122189638"
    },
    "316620751": {
      "phone": "+7 (812) 218-96-38",
      "notFormattedPhone": "78122189638"
    },
    "295780269": {
      "phone": "+7 (812) 218-96-38",
      "notFormattedPhone": "78122189638"
    },
    "317804282": {
      "phone": "+7 (812) 218-96-38",
      "notFormattedPhone": "78122189638"
    },
    "318130470": {
      "phone": "+7 (812) 218-96-38",
      "notFormattedPhone": "78122189638"
    },
    "318582792": {
      "phone": "+7 (812) 218-96-38",
      "notFormattedPhone": "78122189638"
    },
    "318635000": {
      "phone": "+7 (812) 218-96-38",
      "notFormattedPhone": "78122189638"
    },
    "298747095": {
      "phone": "+7 (812) 218-96-38",
      "notFormattedPhone": "78122189638"
    },
    "307203609": {
      "phone": "+7 (812) 218-96-38",
      "notFormattedPhone": "78122189638"
    },
    "313383032": {
      "phone": "+7 (812) 218-96-38",
      "notFormattedPhone": "78122189638"
    },
    "312765648": {
      "phone": "+7 (812) 218-96-38",
      "notFormattedPhone": "78122189638"
    },
    "312742483": {
      "phone": "+7 (812) 218-96-38",
      "notFormattedPhone": "78122189638"
    },
    "318650018": {
      "phone": "+7 (812) 218-96-38",
      "notFormattedPhone": "78122189638"
    },
    "317134984": {
      "phone": "+7 (812) 218-96-38",
      "notFormattedPhone": "78122189638"
    },
    "318582981": {
      "phone": "+7 (812) 218-96-38",
      "notFormattedPhone": "78122189638"
    },
    "309177593": {
      "phone": "+7 (812) 218-96-38",
      "notFormattedPhone": "78122189638"
    },
    "314476167": {
      "phone": "+7 (812) 218-96-38",
      "notFormattedPhone": "78122189638"
    },
    "318374207": {
      "phone": "+7 (812) 218-96-38",
      "notFormattedPhone": "78122189638"
    },
    "317133706": {
      "phone": "+7 (812) 218-96-38",
      "notFormattedPhone": "78122189638"
    },
    "314496871": {
      "phone": "+7 (812) 218-96-38",
      "notFormattedPhone": "78122189638"
    },
    "307839543": {
      "phone": "+7 (812) 218-96-38",
      "notFormattedPhone": "78122189638"
    },
    "312733859": {
      "phone": "+7 (812) 218-96-38",
      "notFormattedPhone": "78122189638"
    },
    "317133980": {
      "phone": "+7 (812) 218-96-38",
      "notFormattedPhone": "78122189638"
    },
    "294211010": {
      "phone": "+7 (812) 218-96-38",
      "notFormattedPhone": "78122189638"
    },
    "312466112": {
      "phone": "+7 (812) 218-96-38",
      "notFormattedPhone": "78122189638"
    },
    "306267260": {
      "phone": "+7 (812) 218-96-38",
      "notFormattedPhone": "78122189638"
    },
    "314600585": {
      "phone": "+7 (812) 218-96-38",
      "notFormattedPhone": "78122189638"
    },
    "318656950": {
      "phone": "+7 (812) 218-96-38",
      "notFormattedPhone": "78122189638"
    }
  }
}